{
  "일련번호": 101304445,
  "수감자": "이상",
  "인격": "약지 점묘파 스튜던트 이상",
  "동기화": 4,
  "레벨": 45,
  "체력": 178,
  "최저속도": 3,
  "최고속도": 7,
  "수비레벨": 43,
  "내성정보": {
    "참격": "보통",
    "관통": "내성",
    "타격": "취약"
  },
  "소속": "약지",
  "등급": 3,
  "출시시기": "2024-05-16",
  "스킬": {
    "공격스킬1": {
      "코인개수": 3,
      "스킬이름": "덧칠",
      "공격레벨": 48,
      "공격유형": "관통",
      "죄악속성": "우울",
      "스킬위력": 2,
      "코인위력": 3,
      "공격가중치": 1,
      "코인별효과": {
        "0": [
          "대상의 출혈이 6 이상이면 합 위력 +1"
        ],
        "2": [
          "[앞면 적중시] 화상, 출혈, 진동, 파열, 침잠 중 무작위 1개 효과의 횟수 2 증가"
        ],
        "3": [
          "[적중시] 출혈 2 부여"
        ]
      }
    },
    "공격스킬2": {
      "코인개수": 1,
      "스킬이름": "혈점묘화",
      "공격레벨": 48,
      "공격유형": "관통",
      "죄악속성": "색욕",
      "스킬위력": 8,
      "코인위력": 8,
      "공격가중치": 1,
      "코인별효과": {
        "0": [
          "대상의 출혈 3 당 합 위력 +1 (최대 2)",
          "대상의 출혈 횟수 3 당 코인 위력 +1 (최대 2)"
        ],
        "1": [
          "[적중시] 40% 확률로 코인 재사용. 대상이 보유한 부정적인 효과 1개 당 재사용 확률 +20% (스킬당 최대 2회 재사용 가능)",
          "[적중시] 출혈 횟수 1 증가",
          "[적중시] 화상, 출혈, 진동, 파열, 침잠 중 무작위 1개 효과의 횟수 3 증가"
        ]
      }
    },
    "공격스킬3": {
      "코인개수": 4,
      "스킬이름": "핏방울 채색",
      "공격레벨": 48,
      "공격유형": "관통",
      "죄악속성": "나태",
      "스킬위력": 3,
      "코인위력": 3,
      "공격가중치": 1,
      "코인별효과": {
        "0": [
          "대상의 출혈 3 당 합 위력 +1 (최대 2)",
          "대상의 출혈 횟수 3 당 코인 위력 +1 (최대 2)"
        ],
        "2": [
          "[적중시] 출혈 횟수 1 증가. 대상이 보유한 부정적인 효과가 3개 이상이면 추가 2 증가",
          "[적중시] 화상, 출혈, 진동, 파열, 침잠 중 무작위 1개 효과의 횟수 3 증가"
        ],
        "3": [
          "[적중시] 출혈 1 부여. 대상이 보유한 부정적인 효과가 3개 이상이면 2 추가 부여",
          "[적중시] 화상, 출혈, 진동, 파열, 침잠 중 무작위 1개 효과의 위력 2 부여"
        ],
        "4": [
          "대상이 보유한 부정적인 효과 1개당 피해량 +25% (최대 125%)",
          "[공격 종료시] 대상이 흐트러졌거나 사망했으면, 부정적인 효과를 가장 적게 보유한 적 2명에게 화상, 출혈, 진동, 파열, 침잠 중 무작위 1개 효과 2 부여"
        ]
      }
    },
    "수비스킬1": {
      "코인개수": 1,
      "스킬이름": "붓 털기",
      "공격레벨": 46,
      "수비유형": "방어",
      "죄악속성": "색욕",
      "스킬위력": 10,
      "코인위력": 4,
      "공격가중치": 1,
      "코인별효과": {
        "0": [
          "대상의 출혈 1 당 기본 위력 +1 (최대 10)"
        ]
      }
    }
  },
  "패시브": {
    "1": {
      "이름": "과제평가",
      "죄악": "색욕",
      "수량": 4,
      "조건": "보유",
      "내용": [
        "- 적중시 대상에게 출혈이 4 이상 있으면 정신력 2 회복",
        "- 대상이 보유한 부정적인 효과 1개당 정신력 1 추가 회복.(최대 3)",
        "- 이 효과로 정신력 회복 시 자신의 정신력이 최대면 다음 턴에 공격 레벨 증가 2 얻음",
        "(턴 당 패시브 최대 발동 횟수 : 4회)"
      ]
    },
    "2": {
      "이름": "혈점묘파",
      "내용": [
        "이 인격은 출혈을 부여하는 인격으로만 취급됨.",
        "랜덤으로 화상, 출혈, 진동, 파열, 침잠을 부여하는 스킬이 이 효과로 인해서 해당 키워드를 부여하는 스킬로 취급되지 않음."
      ]
    }
  },
  "서포트 패시브": {
    "이름": "미학견습",
    "죄악": "색욕",
    "수량": 4,
    "조건": "보유",
    "내용": [
      "- 정신력이 가장 낮은 아군이 공격 적중시 대상이 보유한 부정적인 효과 1개당 정신력 2 회복(최대 6)",
      "- 대상에게 출혈이 있으면 3 추가 회복",
      "(턴 당 패시브 최대 발동 횟수 : 2회)"
    ]
  },
  "공격유형": [
    "관통"
  ],
  "죄악속성": [
    "나태",
    "색욕",
    "우울"
  ],
  "키워드": {
    "대표": [
      "출혈"
    ],
    "기본": [
      "공격 레벨"
    ],
    "특별": []
  },
  "서포트 키워드": {
    "대표": [
      "출혈"
    ],
    "기본": [
      "정신력 회복"
    ],
    "특별": []
  }
}